cbaxter1988_utils/__init__.py
cbaxter1988_utils/auth_utils.py
cbaxter1988_utils/aws_cognito_utils.py
cbaxter1988_utils/aws_dynamodb_utils.py
cbaxter1988_utils/aws_event_bridge_utils.py
cbaxter1988_utils/aws_lambda_utils.py
cbaxter1988_utils/aws_secrets_manager_utils.py
cbaxter1988_utils/aws_utils.py
cbaxter1988_utils/cloudwatch_utils.py
cbaxter1988_utils/core_utils.py
cbaxter1988_utils/dataclass_utils.py
cbaxter1988_utils/decorators.py
cbaxter1988_utils/environment_utils.py
cbaxter1988_utils/flask_utils.py
cbaxter1988_utils/iter_utils.py
cbaxter1988_utils/log_utils.py
cbaxter1988_utils/pagination_utils.py
cbaxter1988_utils/pika_utils.py
cbaxter1988_utils/pymongo_utils.py
cbaxter1988_utils/requests_utils.py
cbaxter1988_utils/serialization_utils.py
cbaxter1988_utils/test_utils.py
cbaxter1988_utils/time_utils.py
cbaxter1988_utils/daos/__init__.py
cbaxter1988_utils/daos/base_dao.py
cbaxter1988_utils/daos/dynamodb_dao.py
cbaxter1988_utils/daos/mongodb_dao.py
cbaxter1988_utils/models/__init__.py
cbaxter1988_utils/models/ddd_models.py
cbaxter1988_utils/models/factory.py
cbaxter1988_utils/models/http_models/__init__.py
cbaxter1988_utils/models/http_models/problem_detail_rfc_7807_model.py
cbaxter1988_utils/tests/__init__.py
cbaxter1988_utils/tests/conftest.py
cbaxter1988_utils/tests/const.py
cbaxter1988_utils/tests/test_auth_utils.py
cbaxter1988_utils/tests/test_aws_cognito_utils.py
cbaxter1988_utils/tests/test_core_utils.py
cbaxter1988_utils/tests/test_dataclass_utils.py
cbaxter1988_utils/tests/test_flask_utils.py
cbaxter1988_utils/tests/test_pagination_utils.py
cbaxter1988_utils/tests/test_pika_utils.py
cbaxter1988_utils/tests/test_pymongo_utils.py
cbaxter1988_utils/tests/test_serialization_utils.py
cbaxter1988_utils-0.9.4.dist-info/METADATA
cbaxter1988_utils-0.9.4.dist-info/WHEEL
cbaxter1988_utils-0.9.4.dist-info/top_level.txt
cbaxter1988_utils-0.9.4.dist-info/RECORD
