Metadata-Version: 2.1
Name: cbaxter1988_utils
Version: 0.9.4
Summary: A Package containing my utils
Home-page: https://github.com/cbaxter1988/utils.git
Author: Courtney S Baxter Jr
Author-email: cbaxtertech@gmail.com
License: UNKNOWN
Platform: UNKNOWN
